mlm8s/__init__.py
mlm8s/chaos.py
mlm8s/connect.py
mlm8s/custom_metrices.py
mlm8s/data/english_names.npy
mlm8s/data/opinionated.npy
mlm8s/data/stopwords.npy
mlm8s/generator.py
mlm8s/helpers.py
mlm8s/hypermodel.py
mlm8s/lattice.py
mlm8s/numeric.py
mlm8s/overview - metrics
mlm8s/paths.py
mlm8s/plot.py
mlm8s/polynom.py
mlm8s/rounding_loss.py
mlm8s/sparse.py
mlm8s/spiral.py
mlm8s/text.py
mlm8s/training.py
mlm8s/triangle.py
mlm8s/voltera.py
mlm8s-1.0.3.3.dist-info/LICENSE
mlm8s-1.0.3.3.dist-info/METADATA
mlm8s-1.0.3.3.dist-info/WHEEL
mlm8s-1.0.3.3.dist-info/RECORD
